[
    {
        "id": "T001",
        "name": "Light default",
        "colors": {
            "primary": "#333",
            "secondary": "#eee",
            "background": "#fff",
            "body": "#fff",
            "text": "#333",
            "buttonPrimary": {
                "text": "#fff",
                "background": "#333"
            },
            "buttonSecondary": {
                "text": "#333",
                "background": "#fff"
            },
            "link": {
                "text": "#1771bb",
                "background": "#fff"
            },
            "boxShadow": "rgba(100, 100, 111, 0.2)"
        },
        "font": ""
    },
    {
        "id": "T002",
        "name": "Dark default",
        "colors": {
            "primary": "#fff",
            "secondary": "#eee",
            "background": "#222831",
            "body": "#222831",
            "text": "#fff",
            "buttonPrimary": {
                "text": "#222831",
                "background": "#fff"
            },
            "buttonSecondary": {
                "text": "#fff",
                "background": "#222831"
            },
            "link": {
                "text": "#fae3b4",
                "background": "#fff"
            },
            "boxShadow": "rgba(193, 122, 235, 0.4)"
        },
        "font": "Arial"
    },
    {
        "id": "T003",
        "name": "Sea Wave",
        "colors": {
            "primary": "#0d47a1",
            "secondary": "#eee",
            "background": "#9be7ff",
            "body": "#9be7ff",
            "text": "#0d47a1",
            "buttonPrimary": {
                "text": "#0d47a1",
                "background": "#fff"
            },
            "buttonSecondary": {
                "text": "#fff",
                "background": "#0d47a1"
            },
            "link": {
                "text": "#0d47a1",
                "background": "#fff"
            },
            "boxShadow": "rgba(100, 100, 111, 0.2)"
        },
        "font": "Ubuntu"
    }
]
